LICENSE
MANIFEST.in
README.md
README.pypi
pyproject.toml
requirements.txt
setup.py
Orange3_spectroscopy_plus.egg-info/PKG-INFO
Orange3_spectroscopy_plus.egg-info/SOURCES.txt
Orange3_spectroscopy_plus.egg-info/dependency_links.txt
Orange3_spectroscopy_plus.egg-info/entry_points.txt
Orange3_spectroscopy_plus.egg-info/namespace_packages.txt
Orange3_spectroscopy_plus.egg-info/not-zip-safe
Orange3_spectroscopy_plus.egg-info/requires.txt
Orange3_spectroscopy_plus.egg-info/top_level.txt
orangecontrib/__init__.py
orangecontrib/spectroscopy_plus/__init__.py
orangecontrib/spectroscopy_plus/io/__init__.py
orangecontrib/spectroscopy_plus/io/gwyddion.py
orangecontrib/spectroscopy_plus/io/neaspec.py
orangecontrib/spectroscopy_plus/io/perkinelmer.py
orangecontrib/spectroscopy_plus/io/utils/__init__.py
orangecontrib/spectroscopy_plus/io/utils/metaformatter.py
orangecontrib/spectroscopy_plus/io/utils/utils.py
orangecontrib/spectroscopy_plus/preprocess/__init__.py
orangecontrib/spectroscopy_plus/preprocess/chiptransition.py
orangecontrib/spectroscopy_plus/tests/__init__.py
orangecontrib/spectroscopy_plus/utils/__init__.py
orangecontrib/spectroscopy_plus/utils/plots/__init__.py
orangecontrib/spectroscopy_plus/utils/plots/contrastingcolormethod.py
orangecontrib/spectroscopy_plus/widgets/__init__.py
orangecontrib/spectroscopy_plus/widgets/owmultihyperspectra.py
orangecontrib/spectroscopy_plus/widgets/owshift.py
orangecontrib/spectroscopy_plus/widgets/owtransformview.py
orangecontrib/spectroscopy_plus/widgets/components/__init__.py
orangecontrib/spectroscopy_plus/widgets/components/editors/__init__.py
orangecontrib/spectroscopy_plus/widgets/components/editors/oweditor.py
orangecontrib/spectroscopy_plus/widgets/components/editors/tableview.py
orangecontrib/spectroscopy_plus/widgets/components/editors/hypereditor/__init__.py
orangecontrib/spectroscopy_plus/widgets/components/editors/hypereditor/integrationtypes/__init__.py
orangecontrib/spectroscopy_plus/widgets/components/editors/hypereditor/integrationtypes/base.py
orangecontrib/spectroscopy_plus/widgets/components/editors/hypereditor/integrationtypes/fromspectra.py
orangecontrib/spectroscopy_plus/widgets/components/editors/hypereditor/integrationtypes/usefeature.py
orangecontrib/spectroscopy_plus/widgets/components/editors/hypereditor/integrationtypes/usergb.py
