Metadata-Version: 2.1
Name: Orange3-spectroscopy-plus
Version: 0.1.0
Summary: Add-on that extends the orange-spectroscopy
Home-page: UNKNOWN
License: GPLv3+
Keywords: orange3 add-on,spectroscopy,plus
Platform: UNKNOWN
License-File: LICENSE
